mutwo/music_converters/__init__.py
mutwo/music_converters/configurations.py
mutwo/music_converters/grace_notes.py
mutwo/music_converters/instruments.py
mutwo/music_converters/metricities.py
mutwo/music_converters/parsers.py
mutwo/music_converters/playing_indicators.py
mutwo/music_converters/spectrals.py
mutwo/music_events/__init__.py
mutwo/music_events/configurations.py
mutwo/music_events/music.py
mutwo/music_generators/__init__.py
mutwo/music_generators/constants.py
mutwo/music_parameters/__init__.py
mutwo/music_parameters/abc.py
mutwo/music_parameters/ambituses.py
mutwo/music_parameters/commas.py
mutwo/music_parameters/notation_indicators.py
mutwo/music_parameters/pitch_intervals.py
mutwo/music_parameters/playing_indicators.py
mutwo/music_parameters/scales.py
mutwo/music_parameters/volumes.py
mutwo/music_parameters/configurations/__init__.py
mutwo/music_parameters/configurations/instruments.py
mutwo/music_parameters/configurations/lyrics.py
mutwo/music_parameters/configurations/pitch_intervals.py
mutwo/music_parameters/configurations/pitches.py
mutwo/music_parameters/configurations/volumes.py
mutwo/music_parameters/constants/__init__.py
mutwo/music_parameters/constants/diatonic_pitch_classes.py
mutwo/music_parameters/constants/instruments.py
mutwo/music_parameters/constants/pitch_intervals.py
mutwo/music_parameters/constants/pitches.py
mutwo/music_parameters/constants/playing_indicators.py
mutwo/music_parameters/constants/volumes.py
mutwo/music_parameters/instruments/Bassoon.py
mutwo/music_parameters/instruments/BfClarinet.py
mutwo/music_parameters/instruments/CelticHarp.py
mutwo/music_parameters/instruments/EfClarinet.py
mutwo/music_parameters/instruments/Flute.py
mutwo/music_parameters/instruments/Oboe.py
mutwo/music_parameters/instruments/Piccolo.py
mutwo/music_parameters/instruments/__init__.py
mutwo/music_parameters/instruments/general.py
mutwo/music_parameters/lyrics/__init__.py
mutwo/music_parameters/lyrics/text_based_lyrics.py
mutwo_music-0.29.0.dist-info/licenses/LICENSE
mutwo_music-0.29.0.dist-info/METADATA
mutwo_music-0.29.0.dist-info/WHEEL
mutwo_music-0.29.0.dist-info/top_level.txt
mutwo_music-0.29.0.dist-info/RECORD
