Metadata-Version: 2.4
Name: mutwo.music
Version: 0.29.0
Summary: music extension for event based framework for generative art
Home-page: https://github.com/mutwo-org/mutwo.music
Author: Levin Eric Zimmermann
Author-email: levin.eric.zimmermann@posteo.eu
License: GPL
Project-URL: Documentation, https://mutwo-org.github.io
Classifier: Development Status :: 3 - Alpha
Classifier: Intended Audience :: Developers
Classifier: Intended Audience :: End Users/Desktop
Classifier: Intended Audience :: Education
Classifier: License :: OSI Approved :: GNU General Public License v3 or later (GPLv3+)
Classifier: Operating System :: Unix
Classifier: Programming Language :: Python :: 3 :: Only
Classifier: Programming Language :: Python :: 3.10
Classifier: Programming Language :: Python :: 3.11
Classifier: Topic :: Artistic Software
Classifier: Topic :: Multimedia
Classifier: Topic :: Multimedia :: Sound/Audio
Classifier: Topic :: Multimedia :: Sound/Audio :: MIDI
Requires-Python: >=3.10, <4
License-File: LICENSE
Requires-Dist: mutwo.core<3.0.0,>=2.0.0
Requires-Dist: epitran<1.25,>=1.23
Requires-Dist: sympy<2.0.0,>=1.10.1
Requires-Dist: python-ranges<2.0.0,>=1.2.0
Provides-Extra: testing
Requires-Dist: pytest>=7.1.1; extra == "testing"
Dynamic: author
Dynamic: author-email
Dynamic: classifier
Dynamic: description
Dynamic: description-content-type
Dynamic: home-page
Dynamic: license
Dynamic: license-file
Dynamic: project-url
Dynamic: provides-extra
Dynamic: requires-dist
Dynamic: requires-python
Dynamic: summary
